wifi_scan.py
wifi_scan-0.0.1.dist-info/entry_points.txt
wifi_scan-0.0.1.dist-info/LICENSE
wifi_scan-0.0.1.dist-info/WHEEL
wifi_scan-0.0.1.dist-info/METADATA
wifi_scan-0.0.1.dist-info/RECORD
