Metadata-Version: 2.1
Name: wifi-scan
Version: 0.0.1
Summary: Scan & report on visible access points (iwlist scan).
Home-page: https://github.com/jesteria/wifi-scan
License: UNKNOWN
Keywords: iwlist
Author: Jesse London
Author-email: jesselondon@gmail.com
Requires-Python: >=3.8
Classifier: Development Status :: 4 - Beta
Classifier: Environment :: Console
Classifier: Intended Audience :: End Users/Desktop
Classifier: License :: OSI Approved :: MIT License
Classifier: Programming Language :: Python
Classifier: Topic :: System :: Networking
Requires-Dist: terminaltables == 3.1.0
